redis_hashring/__init__.py
redis_hashring-0.6.0.dist-info/licenses/LICENSE
redis_hashring-0.6.0.dist-info/METADATA
redis_hashring-0.6.0.dist-info/WHEEL
redis_hashring-0.6.0.dist-info/top_level.txt
redis_hashring-0.6.0.dist-info/RECORD
